setup.py
tikitiki/__init__.py
tikitiki/multilistbox.py
tikitiki/splash.py
tikitiki/tooltip.py
tikitiki/utils.py
tikitiki/working_gif.py
tikitiki.egg-info/PKG-INFO
tikitiki.egg-info/SOURCES.txt
tikitiki.egg-info/dependency_links.txt
tikitiki.egg-info/not-zip-safe
tikitiki.egg-info/top_level.txt