Metadata-Version: 1.0
Name: tikitiki
Version: 0.2
Summary: Cross-platform widget toolkit for tkinter python GUIs
Home-page: http://github.com/rutherford/tikitiki
Author: Matt Rutherford
Author-email: rutherford@clientsideweb.net
License: BSD
Platform: UNKNOWN
